tinygent/__init__.py
tinygent/logging.py
tinygent/agents/__init__.py
tinygent/agents/base_agent.py
tinygent/agents/map_agent.py
tinygent/agents/multi_step_agent.py
tinygent/agents/react_agent.py
tinygent/agents/register.py
tinygent/agents/squad_agent.py
tinygent/agents/middleware/README.md
tinygent/agents/middleware/__init__.py
tinygent/agents/middleware/agent.py
tinygent/agents/middleware/base.py
tinygent/agents/middleware/llm_tool_selector.py
tinygent/agents/middleware/register.py
tinygent/agents/middleware/tool_limiter.py
tinygent/cli/builder.py
tinygent/cli/entry_point.py
tinygent/cli/main.py
tinygent/cli/utils.py
tinygent/cli/commands/terminal.py
tinygent/core/__init__.py
tinygent/core/chat_history.py
tinygent/core/prompt.py
tinygent/core/datamodels/__init__.py
tinygent/core/datamodels/agent.py
tinygent/core/datamodels/agent_hooks.py
tinygent/core/datamodels/cross_encoder.py
tinygent/core/datamodels/embedder.py
tinygent/core/datamodels/llm.py
tinygent/core/datamodels/memory.py
tinygent/core/datamodels/messages.py
tinygent/core/datamodels/middleware.py
tinygent/core/datamodels/tool.py
tinygent/core/datamodels/tool_info.py
tinygent/core/factory/__init__.py
tinygent/core/factory/agent.py
tinygent/core/factory/cross_encoder.py
tinygent/core/factory/embedder.py
tinygent/core/factory/helper.py
tinygent/core/factory/llm.py
tinygent/core/factory/memory.py
tinygent/core/factory/middleware.py
tinygent/core/factory/tool.py
tinygent/core/prompts/agents/__init__.py
tinygent/core/prompts/agents/factory/map_agent.py
tinygent/core/prompts/agents/factory/multi_agent.py
tinygent/core/prompts/agents/factory/react_agent.py
tinygent/core/prompts/agents/factory/squad_agent.py
tinygent/core/prompts/agents/middleware/factory/llm_tool_selector.py
tinygent/core/prompts/agents/middleware/template/llm_tool_selector.py
tinygent/core/prompts/agents/template/map_agent.py
tinygent/core/prompts/agents/template/multi_agent.py
tinygent/core/prompts/agents/template/react_agent.py
tinygent-0.1.1007.dist-info/METADATA
tinygent-0.1.1007.dist-info/WHEEL
tinygent-0.1.1007.dist-info/entry_points.txt
tinygent-0.1.1007.dist-info/licenses/LICENSE
tinygent-0.1.1007.dist-info/RECORD
