Metadata-Version: 2.4
Name: tinygent
Version: 0.1.1007
Summary: Tiny agentic framework for building AI agents which can do more than tiny just tasks.
Project-URL: Homepage, https://github.com/filchy/tinygent
Project-URL: Repository, https://github.com/filchy/tinygent
Project-URL: Issues, https://github.com/filchy/tinygent/issues
Author: Filip Chytil
License-Expression: MIT
License-File: LICENSE
Keywords: agentic,agents,ai,anthropic,framework,llm,openai
Classifier: Development Status :: 3 - Alpha
Classifier: Intended Audience :: Developers
Classifier: License :: OSI Approved :: MIT License
Classifier: Programming Language :: Python :: 3.12
Classifier: Topic :: Scientific/Engineering :: Artificial Intelligence
Classifier: Topic :: Software Development :: Libraries :: Python Modules
Requires-Python: ==3.12.*
Requires-Dist: async-lru>=2.0.5
Requires-Dist: jinja2>=3.1.6
Requires-Dist: langchain-core>=0.3.74
Requires-Dist: opentelemetry-exporter-otlp>=1.38.0
Requires-Dist: opentelemetry-sdk>=1.38.0
Requires-Dist: pydantic>=2.11.7
Requires-Dist: pyyaml>=6.0.2
Requires-Dist: typer>=0.19.2
Provides-Extra: anthropic
Requires-Dist: tinygent-anthropic; extra == 'anthropic'
Provides-Extra: brave
Requires-Dist: tinygent-brave; extra == 'brave'
Provides-Extra: chat
Requires-Dist: tinygent-chat; extra == 'chat'
Provides-Extra: dev
Requires-Dist: mypy>=1.17.1; extra == 'dev'
Requires-Dist: ruff>=0.12.11; extra == 'dev'
Provides-Extra: docs
Requires-Dist: mkdocs-material>=9.7.1; extra == 'docs'
Requires-Dist: mkdocs>=1.6.1; extra == 'docs'
Requires-Dist: mkdocstrings[python]>=1.0.2; extra == 'docs'
Provides-Extra: gemini
Requires-Dist: tinygent-gemini; extra == 'gemini'
Provides-Extra: graph
Requires-Dist: tinygent-graph; extra == 'graph'
Provides-Extra: mistralai
Requires-Dist: tinygent-mistralai; extra == 'mistralai'
Provides-Extra: openai
Requires-Dist: tinygent-openai; extra == 'openai'
Provides-Extra: voyageai
Requires-Dist: tinygent-voyageai; extra == 'voyageai'
